src/alu.v
module alu(d1, d2, result, control);
  input wire [31:0] d1;
  input wire [31:0] d2;
  output wire [31:0] result;
  input wire [3:0] control;
  assign result = (control == 4'b0000) ? (d1 + d2) :       // ADD
                  (control == 4'b0001) ? (d1 << d2[4:0]) : // SLL
                  (control == 4'b0010) ? (($signed(d1) < $signed(d2)) ? 32'h00000001 : 32'h00000000) : // SLT
                  (control == 4'b0011) ? ((d1 < d2) ? 32'h00000001 : 32'h00000000) : // SLTU
                  (control == 4'b0100) ? (d1 ^ d2) :       // XOR
                  (control == 4'b0101) ? (d1 >> d2[4:0]) : // SRL
                  (control == 4'b0110) ? (d1 | d2) :       // OR
                  (control == 4'b0111) ? (d1 & d2) :       // AND
                  (control == 4'b1000) ? (d1 - d2) :       // SUB
                  (control == 4'b1101) ? (d1 >>> d2[4:0]) :// SRA
                  32'b0;
endmodule

tb/tb_alu.v
module tb_ALU();
  reg [31:0] d1_tb;
  reg [31:0] d2_tb;
  wire [31:0] result_tb;
  reg [3:0] control_tb;
  
  alu dut (.d1(d1_tb), .d2(d2_tb), .result(result_tb), .control(control_tb));
  
  initial begin
    $dumpfile("dump.vcd");
    $dumpvars(0, tb_ALU);
    d1_tb = 32'hF31474A1;
    d2_tb = 32'hA214673C;
    #10 control_tb = 4'b0000;
    #10 control_tb = 4'b0001;
    #10 control_tb = 4'b0010;
    #10 control_tb = 4'b0011;
    #10 control_tb = 4'b0100;
    #10 control_tb = 4'b0101;
    #10 control_tb = 4'b0110;
    #10 control_tb = 4'b0111;
    #10 control_tb = 4'b1000;
    #10 control_tb = 4'b1001;
    #10 control_tb = 4'b1010;
    #10 control_tb = 4'b1011;
    #10 control_tb = 4'b1100;
    #10 control_tb = 4'b1101;
    #10 control_tb = 4'b1110;
    #10 control_tb = 4'b1111;
    #10 $finish;
  end
endmodule

pre_sim/alu.vcd
$date
	Mon Nov  4 11:36:29 2024
$end
$version
	Icarus Verilog
$end
$timescale
	1s
$end
$scope module tb_ALU $end
$var wire 32 ! result_tb [31:0] $end
$var reg 4 " control_tb [3:0] $end
$var reg 32 # d1_tb [31:0] $end
$var reg 32 $ d2_tb [31:0] $end
$scope module dut $end
$var wire 4 % control [3:0] $end
$var wire 32 & d1 [31:0] $end
$var wire 32 ' d2 [31:0] $end
$var wire 32 ( result [31:0] $end
$upscope $end
$upscope $end
$enddefinitions $end
#0
$dumpvars
bx0xxx00xxxx00xxxxxxxxxxxxxxxx (
b10100010000101000110011100111100 '
b11110011000101000111010010100001 &
bx %
b10100010000101000110011100111100 $
b11110011000101000111010010100001 #
bx "
bx0xxx00xxxx00xxxxxxxxxxxxxxxx !
$end
#10
b10010101001010001101101111011101 !
b10010101001010001101101111011101 (
b0 "
b0 %
#20
b10000000000000000000000000000 !
b10000000000000000000000000000 (
b1 "
b1 %
#30
b0 !
b0 (
b10 "
b10 %
#40
b11 "
b11 %
#50
b1010001000000000001001110011101 !
b1010001000000000001001110011101 (
b100 "
b100 %
#60
b1111 !
b1111 (
b101 "
b101 %
#70
b11110011000101000111011110111101 !
b11110011000101000111011110111101 (
b110 "
b110 %
#80
b10100010000101000110010000100000 !
b10100010000101000110010000100000 (
b111 "
b111 %
#90
b1010001000000000000110101100101 !
b1010001000000000000110101100101 (
b1000 "
b1000 %
#100
b0 !
b0 (
b1001 "
b1001 %
#110
b1010 "
b1010 %
#120
b1011 "
b1011 %
#130
b1100 "
b1100 %
#140
b1111 !
b1111 (
b1101 "
b1101 %
#150
b0 !
b0 (
b1110 "
b1110 %
#160
b1111 "
b1111 %
