src/branchCtrl.v
module branchCtrl(bCtrl, r1, r2, bSel);
  input wire [2:0] bCtrl;
  input wire [31:0] r1;
  input wire [31:0] r2;
  output reg [0:0] bSel;
  
  wire [31:0] condinv = ~r2;
  wire [32:0] sum = {1'b1, condinv} + {1'b0, r1} + {32'b0, 1'b1};
  wire LT = (r1[31] ^ r2[31]) ? r1[31] : sum[32];
  wire LTU = sum[32];
  wire is_sum_zero = sum[31:0] == 32'b0;

  always@(*)
    begin
      bSel = 1'b0;
      case(bCtrl)
        3'b000: bSel = is_sum_zero; // BEQ
          
        3'b001: bSel = !is_sum_zero; // BNE
          
        3'b010: bSel = LT; // BLT
          
        3'b011: bSel = LTU; // BLTU
          
        3'b100: bSel = !LT; // BGE
         
        3'b101: bSel = !LTU; // BGEU
          
        default: bSel = 1'b0;
      endcase
    end
endmodule

tb/tb_branchCtrl.v
module tb_branchCtrl(bCtrl_tb, r1_tb, r2_tb, bSel_tb);
  output logic [2:0] bCtrl_tb;
  output logic [31:0] r1_tb;
  output logic [31:0] r2_tb;
  input logic [0:0] bSel_tb;
  
  branchCtrl dut (.bCtrl(bCtrl_tb),
                  .r1(r1_tb),
                  .r2(r2_tb), 
                  .bSel(bSel_tb)
                 );
  
  initial begin
    $dumpfile("branchCtrl.vcd");
    $dumpvars(0, tb_branchCtrl);
    bCtrl_tb = 3'b000;
    r1_tb = 32'hF0000000;
    r2_tb = 32'hF0000000;
    #1 bCtrl_tb = 3'b001;
    #1 bCtrl_tb = 3'b010;
    #1 r2_tb = 32'hF0000001;
    #1 bCtrl_tb = 3'b011;
    #1 bCtrl_tb = 3'b111;
    #1 bCtrl_tb = 3'b100;
    #1 r2_tb = 32'hFFFFFFFF;
    #1 bCtrl_tb = 3'b101;
    #1 $finish;
endmodule

pre_sim/branchCtrl.vcd
$date
	Mon Nov  4 15:37:18 2024
$end
$version
	Icarus Verilog
$end
$timescale
	1s
$end
$scope module tb_branchCtrl $end
$var wire 1 ! bSel_tb $end
$var reg 3 " bCtrl_tb [2:0] $end
$var reg 32 # r1_tb [31:0] $end
$var reg 32 $ r2_tb [31:0] $end
$scope module dut $end
$var wire 3 % bCtrl [2:0] $end
$var wire 32 & r1 [31:0] $end
$var wire 32 ' r2 [31:0] $end
$var reg 1 ! bSel $end
$upscope $end
$upscope $end
$enddefinitions $end
#0
$dumpvars
b11110000000000000000000000000000 '
b11110000000000000000000000000000 &
b0 %
b11110000000000000000000000000000 $
b11110000000000000000000000000000 #
b0 "
1!
$end
#1
0!
b1 "
b1 %
#2
b10 "
b10 %
#3
b11110000000000000000000000000001 $
b11110000000000000000000000000001 '
#4
b11 "
b11 %
#5
b111 "
b111 %
#6
1!
b100 "
b100 %
#7
1!
b11111111111111111111111111111111 $
b11111111111111111111111111111111 '
#8
0!
b101 "
b101 %
