src/controller.v
module controller (f3, f7, opcode, regWR, memWR, wbCtrl, aluOp, aluS1, aluS2, branchCtrl, memCtrl, doJump, doBranch);
  input wire [2:0] f3;
  input wire [6:0] f7;
  input wire [6:0] opcode;
  output reg regWR, memWR;
  output reg [1:0] wbCtrl;
  output reg [2:0] branchCtrl;
  output reg [2:0] memCtrl;
  output reg aluS1, aluS2, doBranch, doJump;
  output reg [3:0] aluOp;
  
  always@(*)
    begin
      regWR = 1'b0;
      aluS1 = 1'b0;
      aluS2 = 1'b0;
      memWR = 1'b0;
      branchCtrl = 3'b011;
      doJump = 1'b0;
      doBranch = 1'b0;
      memCtrl = 3'b000;
      aluOp = 4'b1001;
      wbCtrl = 2'b11;
      case(opcode)
        7'b0110011: begin // R-type
          regWR = 1'b1;
          wbCtrl = 2'b00;
          aluS1 = 1'b0;
          aluS2 = 1'b1;
          case(f3)
            3'b000: aluOp = (f7[5] == 1'b1) ? {1'b1, f3[2:0]} : {1'b0, f3[2:0]}; // SUB/ADD
            3'b101: aluOp = (f7[5] == 1'b1) ? {1'b1, f3[2:0]} : {1'b0, f3[2:0]}; // SRA/SRL
            3'b001, 3'b010, 3'b011, 3'b100, 3'b110, 3'b111: aluOp = (f7 == 7'b0) ? {1'b0, f3[2:0]} : 4'b1001; // ALU operations/Malformed instruction
          endcase
        end
        
        7'b0010011: begin // I-type (IR-type)
          regWR = 1'b1;
          wbCtrl = 2'b00;
          case(f3)
            3'b101: aluOp = (f7[5] == 1'b1) ? {1'b1, f3[2:0]} : {1'b0, f3[2:0]}; // SRAI/SRLI
            3'b000, 3'b001, 3'b010, 3'b011, 3'b100, 3'b110, 3'b111: aluOp = (f7 == 7'b0) ? {1'b0, f3[2:0]} : 4'b1001;
          endcase
        end
        
        7'b0000011: begin // Loads (IL-type)
          regWR = 1'b1;
          aluOp = 4'b0000;
          wbCtrl = 2'b01;
          case(f3)
            3'b000: memCtrl = 3'b000;   // LB
            3'b001: memCtrl = 3'b001;   // LH
            3'b010: memCtrl = 3'b010;   // LW
            3'b100: memCtrl = 3'b011;   // LBU
            3'b101: memCtrl = 3'b100;   // LHU
            default: memCtrl = 3'b000;  // Malformed instruction
          endcase
        end
        
        7'b0100011: begin // S-type
          memWR = 1'b1;
          aluOp = 4'b0000;
          case(f3)
            3'b000: memCtrl = 3'b101;   // SB
            3'b001: memCtrl = 3'b110;   // SH
            3'b010: memCtrl = 3'b111;   // SW
            default: memCtrl = 3'b000;  // Malformed instruction
          endcase          
        end
        
        7'b1100011: begin // B-type
          branchCtrl = f3;
          doBranch = 1'b1;
          aluS1 = 1'b1;
          aluOp = 4'b0000;
        end
        
        7'b0110111: begin // LUI
          regWR = 1'b1;
          wbCtrl = 2'b00;
          aluOp = 4'b0000;
        end
        
        7'b0010111: begin // AUIPC
          regWR = 1'b1;
          aluS1 = 1'b1;
          wbCtrl = 2'b00;
          aluOp = 4'b0000;
        end
        
        7'b1101111: begin // JAL
          regWR = 1'b1;
          aluS1 = 1'b1;
          wbCtrl = 2'b10;
          aluOp = 4'b0000;
          doJump = 1'b1;
        end
        7'b1100111: begin // JALR
          regWR = 1'b1;
          wbCtrl = 2'b10;
          aluOp = 4'b0000;
          doJump = 1'b1;
        end
        default: begin
          regWR = 1'b0;
          memWR = 1'b0;
          wbCtrl = 2'b11;
          aluS1 = 1'b0;
          aluS2 = 1'b0;
          doJump = 1'b0;
          doBranch = 1'b0;
          branchCtrl = 3'b011;
          aluOp = 4'b1001;
          memCtrl = 3'b000;
        end
    endcase
  end
endmodule

tb/tb_controller.v
module tb_controller();
  reg [2:0] f3_tb;
  reg [6:0] f7_tb;
  reg [6:0] opcode_tb;
  wire regWR_tb;
  wire memWR_tb;
  wire [1:0] wbCtrl_tb;
  wire [2:0] branchCtrl_tb;
  wire [2:0] memCtrl_tb;
  wire aluS1_tb, aluS2_tb;
  wire [3:0] aluOp_tb;
  
  controller dut(.f3(f3_tb), 
                 .f7(f7_tb), 
                 .opcode(opcode_tb), 
                 .regWR(regWR_tb), 
                 .memWR(memWR_tb), 
                 .wbCtrl(wbCtrl_tb), 
                 .aluOp(aluOp_tb), 
                 .aluS1(aluS1_tb), 
                 .aluS2(aluS2_tb), 
                 .branchCtrl(branchCtrl_tb), 
                 .memCtrl(memCtrl_tb),
                 .doBranch(doBranch_tb),
                 .doJump(doJump_tb)
                );
  
  initial begin
    $dumpfile("controller.vcd");
    $dumpvars(0, tb_controller);
    f7_tb = 7'b0;
    opcode_tb = 7'b0;
    f3_tb = 3'b0;
    #1 opcode_tb = 7'b0110011; // R-type
    f3_tb = 3'b000;
    #1 f7_tb = 7'b0100000;
    #1 f3_tb = 3'b001;
    #1 f7_tb = 7'b0;
    #1 f3_tb = 3'b010;
    #1 f3_tb = 3'b011;
    #1 f3_tb = 3'b100;
    #1 f3_tb = 3'b101;
    #1 f7_tb = 7'b0100000;
    #1 f3_tb = 3'b110;
    #1 f7_tb = 7'b0;
    #1 f3_tb = 3'b111;
    #1 opcode_tb = 7'b0010011; // IR-Type
    f3_tb = 3'b000;
    #1 f3_tb = 3'b001;
    #1 f3_tb = 3'b010;
    #1 f3_tb = 3'b011;
    #1 f3_tb = 3'b100;
    #1 f3_tb = 3'b101;
    #1 f3_tb = 3'b110;
    #1 f3_tb = 3'b111;
    #1 opcode_tb = 7'b0000011; // IL-Type
    f3_tb = 3'b000;
    #1 f3_tb = 3'b001;
    #1 f3_tb = 3'b010;
    #1 f3_tb = 3'b011;
    #1 f3_tb = 3'b100;
    #1 f3_tb = 3'b101;
    #1 f3_tb = 3'b110;
    #1 f3_tb = 3'b111;
    #1 opcode_tb = 7'b0100011; // S-type
    f3_tb = 3'b000;
    #1 f3_tb = 3'b001;
    #1 f3_tb = 3'b010;
    #1 f3_tb = 3'b011;
    #1 f3_tb = 3'b100;
    #1 f3_tb = 3'b101;
    #1 f3_tb = 3'b110;
    #1 f3_tb = 3'b111;
    #1 opcode_tb = 7'b1100011; // B-type
    f3_tb = 3'b000;
    #1 f3_tb = 3'b001;
    #1 f3_tb = 3'b010;
    #1 f3_tb = 3'b011;
    #1 f3_tb = 3'b100;
    #1 f3_tb = 3'b101;
    #1 f3_tb = 3'b110;
    #1 f3_tb = 3'b111;
    #1 opcode_tb = 7'b0110111; // LUI
    f3_tb = 3'b000;
    #1 f3_tb = 3'b001;
    #1 f3_tb = 3'b010;
    #1 f3_tb = 3'b011;
    #1 f3_tb = 3'b100;
    #1 f3_tb = 3'b101;
    #1 f3_tb = 3'b110;
    #1 f3_tb = 3'b111;
    #1 opcode_tb = 7'b0010111; // AUPIC
    f3_tb = 3'b000;
    #1 f3_tb = 3'b001;
    #1 f3_tb = 3'b010;
    #1 f3_tb = 3'b011;
    #1 f3_tb = 3'b100;
    #1 f3_tb = 3'b101;
    #1 f3_tb = 3'b110;
    #1 f3_tb = 3'b111;
    #1 opcode_tb = 7'b1101111; // JAL
    f3_tb = 3'b000;
    #1 f3_tb = 3'b001;
    #1 f3_tb = 3'b010;
    #1 f3_tb = 3'b011;
    #1 f3_tb = 3'b100;
    #1 f3_tb = 3'b101;
    #1 f3_tb = 3'b110;
    #1 f3_tb = 3'b111;
    #1 opcode_tb = 7'b0010111; // JALR
    f3_tb = 3'b000;
    #1 f3_tb = 3'b001;
    #1 f3_tb = 3'b010;
    #1 f3_tb = 3'b011;
    #1 f3_tb = 3'b100;
    #1 f3_tb = 3'b101;
    #1 f3_tb = 3'b110;
    #1 f3_tb = 3'b111;
    #1 opcode_tb = 7'b0011111; // default case
    $finish;
  end
endmodule

pre_sim/controller.vcd
$date
	Mon Nov  4 17:12:20 2024
$end
$version
	Icarus Verilog
$end
$timescale
	1s
$end
$scope module tb_controller $end
$var wire 2 ! wbCtrl_tb [1:0] $end
$var wire 1 " regWR_tb $end
$var wire 1 # memWR_tb $end
$var wire 3 $ memCtrl_tb [2:0] $end
$var wire 1 % doJump_tb $end
$var wire 1 & doBranch_tb $end
$var wire 3 ' branchCtrl_tb [2:0] $end
$var wire 1 ( aluS2_tb $end
$var wire 1 ) aluS1_tb $end
$var wire 4 * aluOp_tb [3:0] $end
$var reg 3 + f3_tb [2:0] $end
$var reg 7 , f7_tb [6:0] $end
$var reg 7 - opcode_tb [6:0] $end
$scope module dut $end
$var wire 3 . f3 [2:0] $end
$var wire 7 / f7 [6:0] $end
$var wire 7 0 opcode [6:0] $end
$var reg 4 1 aluOp [3:0] $end
$var reg 1 ) aluS1 $end
$var reg 1 ( aluS2 $end
$var reg 3 2 branchCtrl [2:0] $end
$var reg 1 & doBranch $end
$var reg 1 % doJump $end
$var reg 3 3 memCtrl [2:0] $end
$var reg 1 # memWR $end
$var reg 1 " regWR $end
$var reg 2 4 wbCtrl [1:0] $end
$upscope $end
$upscope $end
$enddefinitions $end
#0
$dumpvars
b11 4
b0 3
b11 2
b1001 1
b0 0
b0 /
b0 .
b0 -
b0 ,
b0 +
b1001 *
0)
0(
b11 '
0&
0%
b0 $
0#
0"
b11 !
$end
#1
b0 *
b0 1
1(
b0 !
b0 4
1"
b110011 -
b110011 0
#2
b0 !
b0 4
b1000 *
b1000 1
1(
1"
b100000 ,
b100000 /
#3
b0 !
b0 4
b1001 *
b1001 1
1(
1"
b1 +
b1 .
#4
b1 *
b1 1
b0 !
b0 4
1(
1"
b0 ,
b0 /
#5
b0 !
b0 4
b10 *
b10 1
1(
1"
b10 +
b10 .
#6
b0 !
b0 4
b11 *
b11 1
1(
1"
b11 +
b11 .
#7
b0 !
b0 4
b100 *
b100 1
1(
1"
b100 +
b100 .
#8
b0 !
b0 4
b101 *
b101 1
1(
1"
b101 +
b101 .
#9
b0 !
b0 4
b1101 *
b1101 1
1(
1"
b100000 ,
b100000 /
#10
b0 !
b0 4
b1001 *
b1001 1
1(
1"
b110 +
b110 .
#11
b110 *
b110 1
b0 !
b0 4
1(
1"
b0 ,
b0 /
#12
b0 !
b0 4
b111 *
b111 1
1(
1"
b111 +
b111 .
#13
b0 !
b0 4
b0 *
b0 1
0(
1"
b0 +
b0 .
b10011 -
b10011 0
#14
b0 !
b0 4
b1 *
b1 1
1"
b1 +
b1 .
#15
b0 !
b0 4
b10 *
b10 1
1"
b10 +
b10 .
#16
b0 !
b0 4
b11 *
b11 1
1"
b11 +
b11 .
#17
b0 !
b0 4
b100 *
b100 1
1"
b100 +
b100 .
#18
b0 !
b0 4
b101 *
b101 1
1"
b101 +
b101 .
#19
b0 !
b0 4
b110 *
b110 1
1"
b110 +
b110 .
#20
b0 !
b0 4
b111 *
b111 1
1"
b111 +
b111 .
#21
b1 !
b1 4
b0 *
b0 1
1"
b0 +
b0 .
b11 -
b11 0
#22
b1 $
b1 3
b1 !
b1 4
b0 *
b0 1
1"
b1 +
b1 .
#23
b1 !
b1 4
b0 *
b0 1
b10 $
b10 3
1"
b10 +
b10 .
#24
b1 !
b1 4
b0 *
b0 1
b0 $
b0 3
1"
b11 +
b11 .
#25
b11 $
b11 3
b1 !
b1 4
b0 *
b0 1
1"
b100 +
b100 .
#26
b1 !
b1 4
b0 *
b0 1
b100 $
b100 3
1"
b101 +
b101 .
#27
b1 !
b1 4
b0 *
b0 1
b0 $
b0 3
1"
b110 +
b110 .
#28
b1 !
b1 4
b0 *
b0 1
1"
b111 +
b111 .
#29
b101 $
b101 3
1#
b11 !
b11 4
b0 *
b0 1
0"
b0 +
b0 .
b100011 -
b100011 0
#30
b0 *
b0 1
b110 $
b110 3
1#
b1 +
b1 .
#31
b0 *
b0 1
b111 $
b111 3
1#
b10 +
b10 .
#32
b0 *
b0 1
b0 $
b0 3
1#
b11 +
b11 .
#33
b0 *
b0 1
1#
b100 +
b100 .
#34
b0 *
b0 1
1#
b101 +
b101 .
#35
b0 *
b0 1
1#
b110 +
b110 .
#36
b0 *
b0 1
1#
b111 +
b111 .
#37
1)
1&
b0 '
b0 2
b0 *
b0 1
0#
b0 +
b0 .
b1100011 -
b1100011 0
#38
b0 *
b0 1
1&
b1 '
b1 2
1)
b1 +
b1 .
#39
b0 *
b0 1
1&
b10 '
b10 2
1)
b10 +
b10 .
#40
b0 *
b0 1
1&
b11 '
b11 2
1)
b11 +
b11 .
#41
b100 '
b100 2
b0 *
b0 1
1&
1)
b100 +
b100 .
#42
b0 *
b0 1
1&
b101 '
b101 2
1)
b101 +
b101 .
#43
b0 *
b0 1
1&
b110 '
b110 2
1)
b110 +
b110 .
#44
b0 *
b0 1
1&
b111 '
b111 2
1)
b111 +
b111 .
#45
b0 !
b0 4
1"
b0 *
b0 1
0&
b11 '
b11 2
0)
b0 +
b0 .
b110111 -
b110111 0
#46
b0 !
b0 4
b0 *
b0 1
1"
b1 +
b1 .
#47
b0 !
b0 4
b0 *
b0 1
1"
b10 +
b10 .
#48
b0 !
b0 4
b0 *
b0 1
1"
b11 +
b11 .
#49
b0 !
b0 4
b0 *
b0 1
1"
b100 +
b100 .
#50
b0 !
b0 4
b0 *
b0 1
1"
b101 +
b101 .
#51
b0 !
b0 4
b0 *
b0 1
1"
b110 +
b110 .
#52
b0 !
b0 4
b0 *
b0 1
1"
b111 +
b111 .
#53
1)
b0 !
b0 4
b0 *
b0 1
1"
b0 +
b0 .
b10111 -
b10111 0
#54
b0 !
b0 4
b0 *
b0 1
1)
1"
b1 +
b1 .
#55
b0 !
b0 4
b0 *
b0 1
1)
1"
b10 +
b10 .
#56
b0 !
b0 4
b0 *
b0 1
1)
1"
b11 +
b11 .
#57
b0 !
b0 4
b0 *
b0 1
1)
1"
b100 +
b100 .
#58
b0 !
b0 4
b0 *
b0 1
1)
1"
b101 +
b101 .
#59
b0 !
b0 4
b0 *
b0 1
1)
1"
b110 +
b110 .
#60
b0 !
b0 4
b0 *
b0 1
1)
1"
b111 +
b111 .
#61
1%
b10 !
b10 4
b0 *
b0 1
1)
1"
b0 +
b0 .
b1101111 -
b1101111 0
#62
b10 !
b10 4
b0 *
b0 1
1%
1)
1"
b1 +
b1 .
#63
b10 !
b10 4
b0 *
b0 1
1%
1)
1"
b10 +
b10 .
#64
b10 !
b10 4
b0 *
b0 1
1%
1)
1"
b11 +
b11 .
#65
b10 !
b10 4
b0 *
b0 1
1%
1)
1"
b100 +
b100 .
#66
b10 !
b10 4
b0 *
b0 1
1%
1)
1"
b101 +
b101 .
#67
b10 !
b10 4
b0 *
b0 1
1%
1)
1"
b110 +
b110 .
#68
b10 !
b10 4
b0 *
b0 1
1%
1)
1"
b111 +
b111 .
#69
b0 !
b0 4
b0 *
b0 1
0%
1)
1"
b0 +
b0 .
b10111 -
b10111 0
#70
b0 !
b0 4
b0 *
b0 1
1)
1"
b1 +
b1 .
#71
b0 !
b0 4
b0 *
b0 1
1)
1"
b10 +
b10 .
#72
b0 !
b0 4
b0 *
b0 1
1)
1"
b11 +
b11 .
#73
b0 !
b0 4
b0 *
b0 1
1)
1"
b100 +
b100 .
#74
b0 !
b0 4
b0 *
b0 1
1)
1"
b101 +
b101 .
#75
b0 !
b0 4
b0 *
b0 1
1)
1"
b110 +
b110 .
#76
b0 !
b0 4
b0 *
b0 1
1)
1"
b111 +
b111 .
#77
b11 !
b11 4
b1001 *
b1001 1
0)
0"
b11111 -
b11111 0
