src/decoder.v
module decoder(instIn, opcode, rd, rs1, rs2, fn3, fn7);
  input wire [31:0] instIn;
  output reg [4:0] rd;
  output reg [4:0] rs1;
  output reg [4:0] rs2;
  output reg [6:0] opcode;
  output reg [2:0] fn3;
  output reg [6:0] fn7;
  always@(*)
    begin
      opcode = instIn[6:0];
      {rd, rs1, rs2, fn3, fn7} = 'b0;
      case(opcode)
        7'b0110111: //LUI
          begin
            rd = instIn[11:7];
          end
        7'b0010111: //JAL
          begin
            rd = instIn[11:7];
          end
        7'b0010111: //AUIPC
          begin
            rd = instIn[11:7];
          end
        7'b1100111: //JALR
          begin
            rd = instIn[11:7];
            rs1 = instIn[19:15];
            fn3 = instIn[14:12];
          end
        7'b1100011: //B-type
          begin
            rs1 = instIn[19:15];
            rs2 = instIn[24:20];
            fn3 = instIn[14:12];
          end
        7'b0000011: //IL-type
          begin 
            rs1 = instIn[19:15];
            rs2 = instIn[24:20];
            rd = instIn[11:7];
            fn3 = instIn[14:12];
          end
        7'b0100011: //S-type
          begin
            rs1 = instIn[19:15];
            rs2 = instIn[24:20];
            fn3 = instIn[14:12];
          end
        7'b0010011: //IR-type
          begin
            rs1 = instIn[19:15];
            rd = instIn[11:7];
            fn3 = instIn[14:12];
            if(fn3 == 3'b101)
              fn7 = instIn[31:25];
            else
              fn7 = 7'b0;
          end
        7'b0110011: //R-type
          begin
            rs1 = instIn[19:15];
            rs2 = instIn[24:20];
            rd = instIn[11:7];
            fn3 = instIn[14:12];
            fn7 = instIn[31:25];
          end
        default:
          begin
            rs1 = 5'b0;
            rs2 = 5'b0;
            rd = 5'b0;
            fn3 = 3'b0;
            fn7 = 7'b0;
          end
      endcase
    end
endmodule

tb/tb_decoder.v
module tb_decoder();
  reg [31:0] instIn_tb;
  wire [4:0] rd_tb;
  wire [4:0] rs1_tb;
  wire [4:0] rs2_tb;
  wire [31:0] instOut_tb;
  wire [6:0] opcode_tb;
  wire [2:0] fn3_tb;
  wire [6:0] fn7_tb;
  
  decoder dut(.instIn(instIn_tb), 
        .opcode(opcode_tb), 
        .rd(rd_tb), 
        .rs1(rs1_tb), 
        .rs2(rs2_tb), 
        .fn3(fn3_tb), 
        .fn7(fn7_tb));
  
  initial begin
    $dumpfile("decoder.vcd");
    $dumpvars(0, tb_decoder);
    #1 instIn_tb = 32'h00848933;
    #1 instIn_tb = 32'h10100493;
    #1 instIn_tb = 32'h0082a223;
    #1 instIn_tb = 32'h0002a303;
    #1 instIn_tb = 32'h014c6463;
    #1 instIn_tb = 32'h7ff080e7;
    #1 instIn_tb = 32'h0000006f;
    #1 instIn_tb = 32'h872370b7;
    #1 instIn_tb = 32'h10000917;
    #1 instIn_tb = 32'h41425313;
    #1 $finish;
  end
endmodule

pre_sim/decoder.vcd
$date
	Wed Nov  6 18:50:53 2024
$end
$version
	Icarus Verilog
$end
$timescale
	1s
$end
$scope module tb_decoder $end
$var wire 5 ! rs2_tb [4:0] $end
$var wire 5 " rs1_tb [4:0] $end
$var wire 5 # rd_tb [4:0] $end
$var wire 7 $ opcode_tb [6:0] $end
$var wire 7 % fn7_tb [6:0] $end
$var wire 3 & fn3_tb [2:0] $end
$var reg 32 ' instIn_tb [31:0] $end
$scope module dut $end
$var wire 32 ( instIn [31:0] $end
$var reg 3 ) fn3 [2:0] $end
$var reg 7 * fn7 [6:0] $end
$var reg 7 + opcode [6:0] $end
$var reg 5 , rd [4:0] $end
$var reg 5 - rs1 [4:0] $end
$var reg 5 . rs2 [4:0] $end
$upscope $end
$upscope $end
$enddefinitions $end
#0
$dumpvars
bx .
bx -
bx ,
bx +
bx *
bx )
bx (
bx '
bx &
bx %
bx $
bx #
bx "
bx !
$end
#1
b10010 #
b10010 ,
b1001 "
b1001 -
b1000 !
b1000 .
b0 &
b0 )
b0 %
b0 *
b110011 $
b110011 +
b100001001000100100110011 '
b100001001000100100110011 (
#2
b1001 #
b1001 ,
b0 "
b0 -
b0 !
b0 .
b10011 $
b10011 +
b10000000100000000010010010011 '
b10000000100000000010010010011 (
#3
b10 &
b10 )
b1000 !
b1000 .
b101 "
b101 -
b0 #
b0 ,
b100011 $
b100011 +
b100000101010001000100011 '
b100000101010001000100011 (
#4
b110 #
b110 ,
b101 "
b101 -
b0 !
b0 .
b10 &
b10 )
b11 $
b11 +
b101010001100000011 '
b101010001100000011 (
#5
b10100 !
b10100 .
b0 #
b0 ,
b11000 "
b11000 -
b110 &
b110 )
b1100011 $
b1100011 +
b1010011000110010001100011 '
b1010011000110010001100011 (
#6
b1 #
b1 ,
b1 "
b1 -
b0 !
b0 .
b0 &
b0 )
b1100111 $
b1100111 +
b1111111111100001000000011100111 '
b1111111111100001000000011100111 (
#7
b0 #
b0 ,
b0 "
b0 -
b1101111 $
b1101111 +
b1101111 '
b1101111 (
#8
b1 #
b1 ,
b110111 $
b110111 +
b10000111001000110111000010110111 '
b10000111001000110111000010110111 (
#9
b10010 #
b10010 ,
b10111 $
b10111 +
b10000000000000000100100010111 '
b10000000000000000100100010111 (
#10
b100000 %
b100000 *
b101 &
b101 )
b100 "
b100 -
b110 #
b110 ,
b10011 $
b10011 +
b1000001010000100101001100010011 '
b1000001010000100101001100010011 (
