src/or2.v
module or2 #(parameter N = 32)(a, b, y);
  input wire [N-1 : 0] a;
  input wire [N-1 : 0] b;
  output wire [N-1 : 0] y;
  assign y = a | b;
endmodule

src/memController.v
/*
module memController(pcP, aluOut, r2, clk, memReady, aluReady, inst, dataR, memCtrl, memDataIn, memDataOut, memType, dataPosOut, dataPosIn, dataSend, spiAddrOut, gpAddrOut, memClk, rst);
  parameter IM_START = 32'h0000_0000;
  parameter IM_STOP = 32'h007F_FFFF;
  parameter DM_START = 32'h0080_0000;
  parameter DM_STOP = 32'h00FF_FFFF;
  
  parameter GPO_START = 32'h0100_0000;
  parameter GPO_STOP = 32'h0100_0007;
  parameter GPI_START = 32'h0100_0008;
  parameter GPI_STOP = 32'h0100_000F;
  
  input wire [31:0] pcP, aluOut, r2;
  input wire clk, memReady, aluReady, rst;
  output reg [31:0] inst, dataR;
  input wire [2:0] memCtrl;
  output reg [31:0] memDataOut;
  input wire [31:0] memDataIn;
  output reg [1:0] memType = 2'b00;
  input wire [2:0] dataPosIn;
  output reg [2:0] dataPosOut;
  output reg dataSend;
  output reg [23:0] spiAddrOut;
  output reg [3:0] gpAddrOut;
  input wire memClk;
  
  wire delayClk, tmpClk; 
  reg dataWait;
  reg instWait;
  reg [31:0] dataInBuffer;
  
  or2 #(1) clkbuf1 (.a(clk), .b(clk), .y(tmpClk));
  or2 #(1) clkbuf2 (.a(tmpClk), .b(tmpClk), .y(delayClk));
  
  
 // Pre-fetch Instruction Logic
  always @(delayClk)
    begin
      spiAddrOut <= ((pcP >= IM_START) && (pcP <= IM_STOP)) ? pcP[23:0] : 24'h00_0000; 
      instWait <= 1'b1;
      memType <= 2'b11;
    end
  
  // Data In Accumalator && Data Sender
  always @(posedge memClk)
    begin
      if(dataSend == 1'b0)
        begin
          case(dataPosIn)
            3'b000: dataInBuffer[3:0] <= memDataIn[3:0];
            3'b100: dataInBuffer[7:4] <= memDataIn[3:0];
            3'b001: dataInBuffer[11:8] <= memDataIn[3:0];
            3'b101: dataInBuffer[15:12] <= memDataIn[3:0];
            3'b010: dataInBuffer[19:16] <= memDataIn[3:0];
            3'b110: dataInBuffer[23:20] <= memDataIn[3:0];
            3'b011: dataInBuffer[27:24] <= memDataIn[3:0];
            3'b111: dataInBuffer[31:28] <= memDataIn[3:0];
          endcase
        end
      if(dataSend == 1'b1)
        begin
          case(dataPosOut)
            3'b000: begin memDataOut[3:0] <= r2[3:0]; dataPosOut <= 3'b100; end
            3'b100: begin memDataOut[3:0] <= r2[7:4]; dataPosOut <= 3'b001; end
            3'b001: begin memDataOut[3:0] <= r2[11:8]; dataPosOut <= 3'b101; end
            3'b101: begin memDataOut[3:0] <= r2[15:12]; dataPosOut <= 3'b010; end
            3'b010: begin memDataOut[3:0] <= r2[19:16]; dataPosOut <= 3'b110; end
            3'b110: begin memDataOut[3:0] <= r2[23:20]; dataPosOut <= 3'b011; end
            3'b011: begin memDataOut[3:0] <= r2[27:24]; dataPosOut <= 3'b111; end
            3'b111: begin memDataOut[3:0] <= r2[31:28]; dataPosOut <= 3'b000; dataSend <= 1'b0; end
          endcase
        end
    end
  
  // Post-fetch Instruction Logic
  always @(instWait && memReady)
    begin
      inst[31:0] <= dataInBuffer[31:0];
      instWait <= 1'b0;
    end
  
  // Pre-fetch Load Logic
  always @(aluReady)
    begin
      if((memCtrl == 3'b000)) // Load Byte
        begin
          memType <= 2'b01;
          dataWait <= (((aluOut >= IM_START) && (aluOut <= DM_STOP))) ? 1'b1 : 1'b0;
        end
      if((memCtrl == 3'b011)) // Load Byte Unsigned
        begin
          memType <= 2'b01;
          dataWait <= (((aluOut >= IM_START) && (aluOut <= DM_STOP)) || ((aluOut >= GPI_START) && (aluOut <= GPI_STOP))) ? 1'b1 : 1'b0;
        end
      if((memCtrl == 3'b001)||(memCtrl == 3'b100)) // Load Halfword (S/U)
        begin
          memType <= 2'b10;
          dataWait <= ((aluOut >= IM_START) && (aluOut <= DM_STOP)) ? 1'b1 : 1'b0;
        end
      if(memCtrl == 3'b010) // Load Word
        begin
          memType <= 2'b11;
          dataWait <= ((aluOut >= IM_START) && (aluOut <= DM_STOP)) ? 1'b1 : 1'b0;
        end
      if(memCtrl == 3'b101)  // Store Byte
        begin
          memType <= 2'b01;
          dataSend <= ((aluOut >= IM_START) && (aluOut <= GPO_STOP)) ? 1'b1 : 1'b0;
        end
      if(memCtrl == 3'b110)  // Store Halfword
        begin
          memType <= 2'b10;
          dataSend <= ((aluOut >= IM_START) && (aluOut <= DM_STOP)) ? 1'b1 : 1'b0;
        end
      if(memCtrl == 3'b111)  // Store Word
        begin
          memType <= 2'b11;
          dataSend <= ((aluOut >= IM_START) && (aluOut <= DM_STOP)) ? 1'b1 : 1'b0;
        end
      gpAddrOut <= ((aluOut >= GPO_START) && (aluOut <= GPI_STOP)) ? aluOut[3:0] : 4'b0000;
      spiAddrOut <= ((aluOut >= IM_START) && (aluOut <= DM_STOP)) ? aluOut[23:0] : 24'h80_0000;
    end
  
  // Post-fetch Load Logic  
  always @(dataWait && memReady)
    begin
      if(memCtrl == 3'b011) // LBU
        dataInBuffer[31:8] <= 24'b0;
      if(memCtrl == 3'b100) // LHU
        dataInBuffer[31:16] <= 16'b0;
      if(memCtrl == 3'b001) // LH
        dataInBuffer[31:16] <= {16{dataInBuffer[15]}};
      if(memCtrl == 3'b000) // LB
        dataInBuffer[31:8] <= {24{dataInBuffer[7]}};
      dataR[31:0] <= dataInBuffer[31:0];
      dataWait <= 1'b0;
    end
endmodule
*/
module memController(pcP, aluOut, r2, clk, memReady, aluReady, inst, dataR, memCtrl, memDataIn, memDataOut, memType, dataPosOut, dataPosIn, dataSend, spiAddrOut, gpAddrOut, memClk, rst);
  parameter IM_START = 32'h0000_0000;
  parameter IM_STOP = 32'h007F_FFFF;
  parameter DM_START = 32'h0080_0000;
  parameter DM_STOP = 32'h00FF_FFFF;
  
  parameter GPO_START = 32'h0100_0000;
  parameter GPO_STOP = 32'h0100_0007;
  parameter GPI_START = 32'h0100_0008;
  parameter GPI_STOP = 32'h0100_000F;
  
  input wire [31:0] pcP, aluOut, r2;
  input wire clk, memReady, aluReady, rst;
  output reg [31:0] inst, dataR;
  input wire [2:0] memCtrl;
  output reg [31:0] memDataOut;
  input wire [31:0] memDataIn;
  output reg [1:0] memType = 2'b00;
  input wire [2:0] dataPosIn;
  output reg [2:0] dataPosOut;
  output reg dataSend;
  output reg [23:0] spiAddrOut;
  output reg [3:0] gpAddrOut;
  input wire memClk;
  
  wire delayClk, tmpClk; 
  reg dataWait;
  reg instWait;
  reg [31:0] dataInBuffer;
  
  or2 #(1) clkbuf1 (.a(clk), .b(clk), .y(tmpClk));
  or2 #(1) clkbuf2 (.a(tmpClk), .b(tmpClk), .y(delayClk));
  
  // Pre-fetch Instruction Logic
  always @(posedge delayClk or posedge rst) begin
    if (rst) begin
      spiAddrOut <= 24'h00_0000;
      instWait <= 1'b0;
      memType <= 2'b00;
    end else begin
      spiAddrOut <= ((pcP >= IM_START) && (pcP <= IM_STOP)) ? pcP[23:0] : 24'h00_0000; 
      instWait <= 1'b1;
      memType <= 2'b11;
    end
  end
  
  // Data In Accumulator && Data Sender
  always @(posedge memClk or posedge rst) begin
    if (rst) begin
      dataInBuffer <= 32'b0;
      dataSend <= 1'b0;
      memDataOut <= 32'b0;
      dataPosOut <= 3'b0;
    end else begin
      if (dataSend == 1'b0) begin
        case (dataPosIn)
          3'b000: dataInBuffer[3:0] <= memDataIn[3:0];
          3'b100: dataInBuffer[7:4] <= memDataIn[3:0];
          3'b001: dataInBuffer[11:8] <= memDataIn[3:0];
          3'b101: dataInBuffer[15:12] <= memDataIn[3:0];
          3'b010: dataInBuffer[19:16] <= memDataIn[3:0];
          3'b110: dataInBuffer[23:20] <= memDataIn[3:0];
          3'b011: dataInBuffer[27:24] <= memDataIn[3:0];
          3'b111: dataInBuffer[31:28] <= memDataIn[3:0];
        endcase
      end
      if (dataSend == 1'b1) begin
        case (dataPosOut)
          3'b000: begin memDataOut[3:0] <= r2[3:0]; dataPosOut <= 3'b100; end
          3'b100: begin memDataOut[3:0] <= r2[7:4]; dataPosOut <= 3'b001; end
          3'b001: begin memDataOut[3:0] <= r2[11:8]; dataPosOut <= 3'b101; end
          3'b101: begin memDataOut[3:0] <= r2[15:12]; dataPosOut <= 3'b010; end
          3'b010: begin memDataOut[3:0] <= r2[19:16]; dataPosOut <= 3'b110; end
          3'b110: begin memDataOut[3:0] <= r2[23:20]; dataPosOut <= 3'b011; end
          3'b011: begin memDataOut[3:0] <= r2[27:24]; dataPosOut <= 3'b111; end
          3'b111: begin memDataOut[3:0] <= r2[31:28]; dataPosOut <= 3'b000; dataSend <= 1'b0; end
        endcase
      end
    end
  end
  
  // Post-fetch Instruction Logic
  always @(*) begin
    if(instWait) begin
    if (rst) begin
      inst <= 32'b0;
      instWait <= 1'b0;
    end else begin
      if(memReady) begin
      inst <= dataInBuffer;
        instWait <= 1'b0; end
    end end
  end
  
  // Pre-fetch Load Logic
  always @(posedge aluReady or posedge rst) begin
    if (rst) begin
      memType <= 2'b00;
      dataWait <= 1'b0;
      dataSend <= 1'b0;
      spiAddrOut <= 24'b0;
      gpAddrOut <= 4'b0;
    end else begin
      if (memCtrl == 3'b000) begin
        memType <= 2'b01;
        dataWait <= ((aluOut >= IM_START) && (aluOut <= DM_STOP)) ? 1'b1 : 1'b0;
      end
      if (memCtrl == 3'b011) begin
        memType <= 2'b01;
        dataWait <= ((aluOut >= IM_START) && (aluOut <= DM_STOP) || ((aluOut >= GPI_START) && (aluOut <= GPI_STOP))) ? 1'b1 : 1'b0;
      end
      if (memCtrl == 3'b001 || memCtrl == 3'b100) begin
        memType <= 2'b10;
        dataWait <= ((aluOut >= IM_START) && (aluOut <= DM_STOP)) ? 1'b1 : 1'b0;
      end
      if (memCtrl == 3'b010) begin
        memType <= 2'b11;
        dataWait <= ((aluOut >= IM_START) && (aluOut <= DM_STOP)) ? 1'b1 : 1'b0;
      end
      if (memCtrl == 3'b101) begin
        memType <= 2'b01;
        dataSend <= ((aluOut >= IM_START) && (aluOut <= GPO_STOP)) ? 1'b1 : 1'b0;
      end
      if (memCtrl == 3'b110) begin
        memType <= 2'b10;
        dataSend <= ((aluOut >= IM_START) && (aluOut <= DM_STOP)) ? 1'b1 : 1'b0;
      end
      if (memCtrl == 3'b111) begin
        memType <= 2'b11;
        dataSend <= ((aluOut >= IM_START) && (aluOut <= DM_STOP)) ? 1'b1 : 1'b0;
      end
      gpAddrOut <= ((aluOut >= GPO_START) && (aluOut <= GPI_STOP)) ? aluOut[3:0] : 4'b0;
      spiAddrOut <= ((aluOut >= IM_START) && (aluOut <= DM_STOP)) ? aluOut[23:0] : 24'h80_0000;
    end
  end
  
  // Post-fetch Load Logic
  always @(*) begin
    if(dataWait&& memReady) begin
    if (rst) begin
      dataR <= 32'b0;
      dataInBuffer <= 32'b0;
      dataWait <= 1'b0;
    end else begin
      if (memCtrl == 3'b011)
        dataInBuffer[31:8] <= 24'b0;
      if (memCtrl == 3'b100)
        dataInBuffer[31:16] <= 16'b0;
      if (memCtrl == 3'b001)
        dataInBuffer[31:16] <= {16{dataInBuffer[15]}};
      if (memCtrl == 3'b000)
        dataInBuffer[31:8] <= {24{dataInBuffer[7]}};
      dataR <= dataInBuffer;
      dataWait <= 1'b0;
    end
    end
  end
endmodule

tb/tb_memController.v
module tb_memController;
  reg [31:0] pcP, aluOut, r2, memDataIn;
  reg clk, memReady, aluReady, memClk, rst;
  reg [2:0] memCtrl, dataPosIn;
  wire [31:0] inst, dataR, memDataOut;
  wire [1:0] memType;
  wire [2:0] dataPosOut;
  wire dataSend;
  wire [23:0] spiAddrOut;
  wire [3:0] gpAddrOut;

  memController dut (
    .pcP(pcP), .aluOut(aluOut), .r2(r2),
    .clk(clk), .memReady(memReady), .aluReady(aluReady),
    .inst(inst), .dataR(dataR),
    .memCtrl(memCtrl), .memDataIn(memDataIn), .memDataOut(memDataOut),
    .memType(memType), .dataPosOut(dataPosOut),
    .dataPosIn(dataPosIn), .dataSend(dataSend),
    .spiAddrOut(spiAddrOut), .gpAddrOut(gpAddrOut),
    .memClk(memClk), .rst(rst)
  );
  
  always begin
    clk = 0;
    #10;
    clk = 1;
    #10;
  end
  
  always begin
    memClk = 0;
    #5;
    memClk = 1;
    #5;
  end

  initial begin
    $dumpfile("memController.vcd");
    $dumpvars(0, tb_memController);
    rst = 1'b1;
    #1 rst = 1'b0;
    // Initialize input signals
    #1;
    pcP = 32'h0000_0000;
    aluOut = 32'h0080_0000;
    r2 = 32'hA5A5_A5A5;
    memDataIn = 32'hF0F0_F0F0;
    memCtrl = 3'b000;
    dataPosIn = 3'b000;
    memReady = 0;
    aluReady = 0;
    #10;
    pcP = 32'h0000_0004; // Within IM range
    #10;
    
    // Load Byte
    memCtrl = 3'b000; // LB
    aluOut = 32'h0080_0004; // Within DM range
    aluReady = 1;
    #10 aluReady = 0; 
    #10;
    memReady = 1; 
    #10 memReady = 0; // Mimic memory ready signal

    // Load Halfword Unsigned
    memCtrl = 3'b100; // LHU
    aluOut = 32'h0080_0008;
    aluReady = 1;
    #10 aluReady = 0; 
    #10;
    memReady = 1; 
    #10 memReady = 0;

    // Load Word
    memCtrl = 3'b010; // LW
    aluOut = 32'h0080_000C;
    aluReady = 1;
    #10 aluReady = 0; #10;
    memReady = 1; #10 memReady = 0;

    // Store Byte
    memCtrl = 3'b101; // SB
    aluOut = 32'h0100_0000; // GPO range
    aluReady = 1;
    #10 aluReady = 0; #10;
    memReady = 1; #10 memReady = 0;

    // Store Word
    memCtrl = 3'b111; // SW
    aluOut = 32'h0080_000C;
    aluReady = 1;
    #10 aluReady = 0; #10;
    memReady = 1; #10 memReady = 0;
    
    // Finish simulation
    #20;
    $finish;
  end

endmodule

pre_sim/memController.vcd
$date
	Sun Nov 10 19:42:33 2024
$end
$version
	Icarus Verilog
$end
$timescale
	1s
$end
$scope module tb_memController $end
$var wire 24 ! spiAddrOut [23:0] $end
$var wire 2 " memType [1:0] $end
$var wire 32 # memDataOut [31:0] $end
$var wire 32 $ inst [31:0] $end
$var wire 4 % gpAddrOut [3:0] $end
$var wire 1 & dataSend $end
$var wire 32 ' dataR [31:0] $end
$var wire 3 ( dataPosOut [2:0] $end
$var reg 32 ) aluOut [31:0] $end
$var reg 1 * aluReady $end
$var reg 1 + clk $end
$var reg 3 , dataPosIn [2:0] $end
$var reg 1 - memClk $end
$var reg 3 . memCtrl [2:0] $end
$var reg 32 / memDataIn [31:0] $end
$var reg 1 0 memReady $end
$var reg 32 1 pcP [31:0] $end
$var reg 32 2 r2 [31:0] $end
$var reg 1 3 rst $end
$scope module dut $end
$var wire 32 4 aluOut [31:0] $end
$var wire 1 * aluReady $end
$var wire 1 + clk $end
$var wire 3 5 dataPosIn [2:0] $end
$var wire 1 - memClk $end
$var wire 3 6 memCtrl [2:0] $end
$var wire 32 7 memDataIn [31:0] $end
$var wire 1 0 memReady $end
$var wire 32 8 pcP [31:0] $end
$var wire 32 9 r2 [31:0] $end
$var wire 1 3 rst $end
$var wire 1 : tmpClk $end
$var wire 1 ; delayClk $end
$var reg 32 < dataInBuffer [31:0] $end
$var reg 3 = dataPosOut [2:0] $end
$var reg 32 > dataR [31:0] $end
$var reg 1 & dataSend $end
$var reg 1 ? dataWait $end
$var reg 4 @ gpAddrOut [3:0] $end
$var reg 32 A inst [31:0] $end
$var reg 1 B instWait $end
$var reg 32 C memDataOut [31:0] $end
$var reg 2 D memType [1:0] $end
$var reg 24 E spiAddrOut [23:0] $end
$scope module clkbuf1 $end
$var wire 1 + a $end
$var wire 1 + b $end
$var wire 1 : y $end
$upscope $end
$scope module clkbuf2 $end
$var wire 1 : a $end
$var wire 1 : b $end
$var wire 1 ; y $end
$upscope $end
$upscope $end
$upscope $end
$enddefinitions $end
#0
$dumpvars
b0 E
b0 D
b0 C
0B
b0 A
b0 @
0?
b0 >
b0 =
b0 <
0;
0:
bx 9
bx 8
bx 7
bx 6
bx 5
bx 4
13
bx 2
bx 1
x0
bx /
bx .
0-
bx ,
0+
x*
bx )
b0 (
b0 '
0&
b0 %
b0 $
b0 #
b0 "
b0 !
$end
#1
03
#2
0*
00
b0 ,
b0 5
b0 .
b0 6
b11110000111100001111000011110000 /
b11110000111100001111000011110000 7
b10100101101001011010010110100101 2
b10100101101001011010010110100101 9
b100000000000000000000000 )
b100000000000000000000000 4
b0 1
b0 8
#5
1-
#10
b11 "
b11 D
1B
1;
1:
0-
1+
#12
b100 1
b100 8
#15
1-
#20
0;
0:
0-
0+
#22
b100000000000000000000100 !
b100000000000000000000100 E
1?
b1 "
b1 D
1*
b100000000000000000000100 )
b100000000000000000000100 4
#25
1-
#30
b11 "
b11 D
b100 !
b100 E
1;
1:
0-
1+
#32
0*
#35
1-
#40
0;
0:
0-
0+
#42
0B
0?
10
#45
1-
#50
0B
1;
1:
0-
1+
#52
b100000000000000000001000 !
b100000000000000000001000 E
1?
b10 "
b10 D
1*
b100000000000000000001000 )
b100000000000000000001000 4
b100 .
b100 6
00
#55
1-
#60
0;
0:
0-
0+
#62
0*
#65
1-
#70
b11 "
b11 D
1B
b100 !
b100 E
1;
1:
0-
1+
#72
0B
0?
10
#75
1-
#80
0;
0:
0-
0+
#82
b100000000000000000001100 !
b100000000000000000001100 E
1?
1*
b100000000000000000001100 )
b100000000000000000001100 4
b10 .
b10 6
00
#85
1-
#90
1B
b100 !
b100 E
1;
1:
0-
1+
#92
0*
#95
1-
#100
0;
0:
0-
0+
#102
0B
0?
10
#105
1-
#110
0B
1;
1:
0-
1+
#112
b100000000000000000000000 !
b100000000000000000000000 E
1&
b1 "
b1 D
1*
b1000000000000000000000000 )
b1000000000000000000000000 4
b101 .
b101 6
00
#115
b100 (
b100 =
b101 #
b101 C
1-
#120
0;
0:
0-
0+
#122
0*
#125
b1 (
b1 =
b1010 #
b1010 C
1-
#130
b11 "
b11 D
1B
b100 !
b100 E
1;
1:
0-
1+
#132
0B
10
#135
b101 (
b101 =
b101 #
b101 C
1-
#140
0;
0:
0-
0+
#142
b100000000000000000001100 !
b100000000000000000001100 E
1*
b100000000000000000001100 )
b100000000000000000001100 4
b111 .
b111 6
00
#145
b10 (
b10 =
b1010 #
b1010 C
1-
#150
1B
b100 !
b100 E
1;
1:
0-
1+
#152
0*
#155
b110 (
b110 =
b101 #
b101 C
1-
#160
0;
0:
0-
0+
#162
0B
10
#165
b11 (
b11 =
b1010 #
b1010 C
1-
#170
0B
1;
1:
0-
1+
#172
00
#175
b111 (
b111 =
b101 #
b101 C
1-
#180
0;
0:
0-
0+
#185
0&
b0 (
b0 =
b1010 #
b1010 C
1-
#190
1B
1;
1:
0-
1+
