src/regFile.v
module regFile #(parameter DATA_WIDTH = 32) (clk, wrEn, rs1, rs2, rd, r1, r2, rst, dIn);
  input wire clk, wrEn, rst;
  input wire [4:0] rs1, rs2, rd;
  input wire [DATA_WIDTH-1:0] dIn;
  output wire [DATA_WIDTH-1:0] r1, r2;
  reg [DATA_WIDTH-1:0] reg_file [0:31];
  integer i = 0;
  initial begin
    for (i = 0; i < 32; i = i + 1) 
      begin
        reg_file[i] = 0;
      end
  end
  always @(posedge clk or posedge rst) begin
    if (rst) begin
      reg_file[0] <= 0;
      reg_file[1] <= 0;
      reg_file[2] <= 0;
      reg_file[3] <= 0;
      reg_file[4] <= 0;
      reg_file[5] <= 0;
      reg_file[6] <= 0;
      reg_file[7] <= 0;
      reg_file[8] <= 0;
      reg_file[9] <= 0;
      reg_file[10] <= 0;
      reg_file[11] <= 0;
      reg_file[12] <= 0;
      reg_file[13] <= 0;
      reg_file[14] <= 0;
      reg_file[15] <= 0;
      reg_file[16] <= 0;
      reg_file[17] <= 0;
      reg_file[18] <= 0;
      reg_file[19] <= 0;
      reg_file[20] <= 0;
      reg_file[21] <= 0;
      reg_file[22] <= 0;
      reg_file[23] <= 0;
      reg_file[24] <= 0;
      reg_file[25] <= 0;
      reg_file[26] <= 0;
      reg_file[27] <= 0;
      reg_file[28] <= 0;
      reg_file[29] <= 0;
      reg_file[30] <= 0;
      reg_file[31] <= 0;
    end else begin
      reg_file[rd] <= (wrEn && rd != 0) ? dIn : reg_file[rd];
    end
  end
/*
  always @(posedge clk) 
    reg_file[rd] <= (wrEn && rd != 0) ? dIn : reg_file[rd];
*/
  // register file read logic (combinational)
  assign r1 = (rs1 != 0 ) ? reg_file[rs1] : 0;
  assign r2 = (rs2 != 0 ) ? reg_file[rs2] : 0;
endmodule

tb/tb_regFile.v
module tb_regFile();
  reg clk_tb, wrEn_tb, rst_tb;
  reg [4:0] rd_tb;
  reg [4:0] rs1_tb;
  reg [4:0] rs2_tb;
  reg [31:0] dIn_tb;
  wire [31:0] r1_tb;
  wire [31:0] r2_tb;
  
  regFile dut (.clk(clk_tb), 
               .wrEn(wrEn_tb), 
               .rd(rd_tb), 
               .rs1(rs1_tb), 
               .rs2(rs2_tb), 
               .r1(r1_tb),
               .r2(r2_tb),
               .dIn(dIn_tb),
               .rst(rst_tb)
              );
  
  always begin
    clk_tb = 0;
    #5;
    clk_tb = 1;
    #5;
  end
  
  initial begin
    $dumpfile("regFile.vcd");
    $dumpvars(0, tb_regFile);
    wrEn_tb = 1'b0;
    rst_tb = 1'b1;
    rs1_tb = 5'd8;
    rs2_tb = 5'd23;
    #1 rst_tb = 1'b0;
    @(posedge clk_tb);
    wrEn_tb = 1'b1; rd_tb = 5'd0; dIn_tb = 32'hFAFAFA00; 
    @(posedge clk_tb);
    wrEn_tb = 1'b1; rd_tb = 5'd1; dIn_tb = 32'hFAFAFA01; 
    @(posedge clk_tb);
    wrEn_tb = 1'b1; rd_tb = 5'd2; dIn_tb = 32'hFAFAFA02; 
    @(posedge clk_tb);
    wrEn_tb = 1'b1; rd_tb = 5'd3; dIn_tb = 32'hFAFAFA03; 
    @(posedge clk_tb);
    wrEn_tb = 1'b1; rd_tb = 5'd4; dIn_tb = 32'hFAFAFA04; 
    @(posedge clk_tb);
    wrEn_tb = 1'b1; rd_tb = 5'd5; dIn_tb = 32'hFAFAFA05; 
    @(posedge clk_tb);
    wrEn_tb = 1'b1; rd_tb = 5'd6; dIn_tb = 32'hFAFAFA06; 
    @(posedge clk_tb);
    wrEn_tb = 1'b1; rd_tb = 5'd7; dIn_tb = 32'hFAFAFA07; 
    @(posedge clk_tb);
    wrEn_tb = 1'b1; rd_tb = 5'd8; dIn_tb = 32'hFAFAFA08; 
    @(posedge clk_tb);
    wrEn_tb = 1'b1; rd_tb = 5'd9; dIn_tb = 32'hFAFAFA09; 
    @(posedge clk_tb);
    wrEn_tb = 1'b1; rd_tb = 5'd10; dIn_tb = 32'hFAFAFA0A; 
    @(posedge clk_tb);
    wrEn_tb = 1'b1; rd_tb = 5'd11; dIn_tb = 32'hFAFAFA0B; 
    @(posedge clk_tb);
    wrEn_tb = 1'b1; rd_tb = 5'd12; dIn_tb = 32'hFAFAFA0C; 
    @(posedge clk_tb);
    wrEn_tb = 1'b1; rd_tb = 5'd13; dIn_tb = 32'hFAFAFA0D; 
    @(posedge clk_tb);
    wrEn_tb = 1'b1; rd_tb = 5'd14; dIn_tb = 32'hFAFAFA0E; 
    @(posedge clk_tb);
    wrEn_tb = 1'b1; rd_tb = 5'd15; dIn_tb = 32'hFAFAFA0F; 
    @(posedge clk_tb);
    wrEn_tb = 1'b1; rd_tb = 5'd16; dIn_tb = 32'hFAFAFA10; 
    @(posedge clk_tb);
    wrEn_tb = 1'b1; rd_tb = 5'd17; dIn_tb = 32'hFAFAFA11; 
    @(posedge clk_tb);
    wrEn_tb = 1'b1; rd_tb = 5'd18; dIn_tb = 32'hFAFAFA12; 
    @(posedge clk_tb);
    wrEn_tb = 1'b1; rd_tb = 5'd19; dIn_tb = 32'hFAFAFA13; 
    @(posedge clk_tb);
    wrEn_tb = 1'b1; rd_tb = 5'd20; dIn_tb = 32'hFAFAFA14; 
    @(posedge clk_tb);
    wrEn_tb = 1'b1; rd_tb = 5'd21; dIn_tb = 32'hFAFAFA15; 
    @(posedge clk_tb);
    wrEn_tb = 1'b1; rd_tb = 5'd22; dIn_tb = 32'hFAFAFA16; 
    @(posedge clk_tb);
    wrEn_tb = 1'b1; rd_tb = 5'd23; dIn_tb = 32'hFAFAFA17; 
    @(posedge clk_tb);
    wrEn_tb = 1'b1; rd_tb = 5'd24; dIn_tb = 32'hFAFAFA18; 
    @(posedge clk_tb);
    wrEn_tb = 1'b1; rd_tb = 5'd25; dIn_tb = 32'hFAFAFA19; 
    @(posedge clk_tb);
    wrEn_tb = 1'b1; rd_tb = 5'd26; dIn_tb = 32'hFAFAFA1A; 
    @(posedge clk_tb);
    wrEn_tb = 1'b1; rd_tb = 5'd27; dIn_tb = 32'hFAFAFA1B; 
    @(posedge clk_tb);
    wrEn_tb = 1'b1; rd_tb = 5'd28; dIn_tb = 32'hFAFAFA1C; 
    @(posedge clk_tb);
    wrEn_tb = 1'b1; rd_tb = 5'd29; dIn_tb = 32'hFAFAFA1D; 
    @(posedge clk_tb);
    wrEn_tb = 1'b1; rd_tb = 5'd30; dIn_tb = 32'hFAFAFA1E; 
    @(posedge clk_tb);
    wrEn_tb = 1'b1; rd_tb = 5'd31; dIn_tb = 32'hFAFAFA1F; 
    @(posedge clk_tb);
    wrEn_tb = 1'b0;
    dIn_tb = 32'b0;
    rd_tb = 5'b0;
    #10;
    rs1_tb = 5'b00001;
    rs2_tb = 5'b00010;
    #10;
    rs1_tb = 5'b00011;
    rs2_tb = 5'b00100;
    #10;
    rs1_tb = 5'b00101;
    rs2_tb = 5'b00110;
    #10;
    rs1_tb = 5'b00111;
    rs2_tb = 5'b01000;
    #10;
    rs1_tb = 5'b01001;
    rs2_tb = 5'b01010;
    #10;
    rs1_tb = 5'b01011;
    rs2_tb = 5'b01100;
    #10;
    rs1_tb = 5'b01101;
    rs2_tb = 5'b01110;
    #10;
    rs1_tb = 5'b01111;
    rs2_tb = 5'b10000;
    #10;
    rs1_tb = 5'b10001;
    rs2_tb = 5'b10010;
    #10;
    rs1_tb = 5'b10011;
    rs2_tb = 5'b10100;
    #10;
    rs1_tb = 5'b10101;
    rs2_tb = 5'b10110;
    #10;
    rs1_tb = 5'b10111;
    rs2_tb = 5'b11000;
    #10;
    rs1_tb = 5'b11001;
    rs2_tb = 5'b11010;
    #10;
    rs1_tb = 5'b11011;
    rs2_tb = 5'b11100;
    #10;
    rs1_tb = 5'b11101;
    rs2_tb = 5'b11110;
    #10;
    rs1_tb = 5'b11111;
    rs2_tb = 5'b00000;
    #10;
    rst_tb = 1'b1;
    #1;
    rst_tb = 1'b0;
    #9;
    $finish;
  end
endmodule

pre_sim/regFile.vcd
$date
	Tue Nov  5 19:23:30 2024
$end
$version
	Icarus Verilog
$end
$timescale
	1s
$end
$scope module tb_regFile $end
$var wire 32 ! r2_tb [31:0] $end
$var wire 32 " r1_tb [31:0] $end
$var reg 1 # clk_tb $end
$var reg 32 $ dIn_tb [31:0] $end
$var reg 5 % rd_tb [4:0] $end
$var reg 5 & rs1_tb [4:0] $end
$var reg 5 ' rs2_tb [4:0] $end
$var reg 1 ( rst_tb $end
$var reg 1 ) wrEn_tb $end
$scope module dut $end
$var wire 1 # clk $end
$var wire 32 * dIn [31:0] $end
$var wire 5 + rd [4:0] $end
$var wire 5 , rs1 [4:0] $end
$var wire 5 - rs2 [4:0] $end
$var wire 1 ( rst $end
$var wire 1 ) wrEn $end
$var wire 32 . r2 [31:0] $end
$var wire 32 / r1 [31:0] $end
$var integer 32 0 i [31:0] $end
$upscope $end
$upscope $end
$enddefinitions $end
#0
$dumpvars
b100000 0
b0 /
b0 .
b10111 -
b1000 ,
bx +
bx *
0)
1(
b10111 '
b1000 &
bx %
bx $
0#
b0 "
b0 !
$end
#1
0(
#5
b11111010111110101111101000000000 $
b11111010111110101111101000000000 *
b0 %
b0 +
1)
1#
#10
0#
#15
b11111010111110101111101000000001 $
b11111010111110101111101000000001 *
b1 %
b1 +
1#
#20
0#
#25
b11111010111110101111101000000010 $
b11111010111110101111101000000010 *
b10 %
b10 +
1#
#30
0#
#35
b11111010111110101111101000000011 $
b11111010111110101111101000000011 *
b11 %
b11 +
1#
#40
0#
#45
b11111010111110101111101000000100 $
b11111010111110101111101000000100 *
b100 %
b100 +
1#
#50
0#
#55
b11111010111110101111101000000101 $
b11111010111110101111101000000101 *
b101 %
b101 +
1#
#60
0#
#65
b11111010111110101111101000000110 $
b11111010111110101111101000000110 *
b110 %
b110 +
1#
#70
0#
#75
b11111010111110101111101000000111 $
b11111010111110101111101000000111 *
b111 %
b111 +
1#
#80
0#
#85
b11111010111110101111101000001000 "
b11111010111110101111101000001000 /
b11111010111110101111101000001000 $
b11111010111110101111101000001000 *
b1000 %
b1000 +
1#
#90
0#
#95
b11111010111110101111101000001001 $
b11111010111110101111101000001001 *
b1001 %
b1001 +
1#
#100
0#
#105
b11111010111110101111101000001010 $
b11111010111110101111101000001010 *
b1010 %
b1010 +
1#
#110
0#
#115
b11111010111110101111101000001011 $
b11111010111110101111101000001011 *
b1011 %
b1011 +
1#
#120
0#
#125
b11111010111110101111101000001100 $
b11111010111110101111101000001100 *
b1100 %
b1100 +
1#
#130
0#
#135
b11111010111110101111101000001101 $
b11111010111110101111101000001101 *
b1101 %
b1101 +
1#
#140
0#
#145
b11111010111110101111101000001110 $
b11111010111110101111101000001110 *
b1110 %
b1110 +
1#
#150
0#
#155
b11111010111110101111101000001111 $
b11111010111110101111101000001111 *
b1111 %
b1111 +
1#
#160
0#
#165
b11111010111110101111101000010000 $
b11111010111110101111101000010000 *
b10000 %
b10000 +
1#
#170
0#
#175
b11111010111110101111101000010001 $
b11111010111110101111101000010001 *
b10001 %
b10001 +
1#
#180
0#
#185
b11111010111110101111101000010010 $
b11111010111110101111101000010010 *
b10010 %
b10010 +
1#
#190
0#
#195
b11111010111110101111101000010011 $
b11111010111110101111101000010011 *
b10011 %
b10011 +
1#
#200
0#
#205
b11111010111110101111101000010100 $
b11111010111110101111101000010100 *
b10100 %
b10100 +
1#
#210
0#
#215
b11111010111110101111101000010101 $
b11111010111110101111101000010101 *
b10101 %
b10101 +
1#
#220
0#
#225
b11111010111110101111101000010110 $
b11111010111110101111101000010110 *
b10110 %
b10110 +
1#
#230
0#
#235
b11111010111110101111101000010111 !
b11111010111110101111101000010111 .
b11111010111110101111101000010111 $
b11111010111110101111101000010111 *
b10111 %
b10111 +
1#
#240
0#
#245
b11111010111110101111101000011000 $
b11111010111110101111101000011000 *
b11000 %
b11000 +
1#
#250
0#
#255
b11111010111110101111101000011001 $
b11111010111110101111101000011001 *
b11001 %
b11001 +
1#
#260
0#
#265
b11111010111110101111101000011010 $
b11111010111110101111101000011010 *
b11010 %
b11010 +
1#
#270
0#
#275
b11111010111110101111101000011011 $
b11111010111110101111101000011011 *
b11011 %
b11011 +
1#
#280
0#
#285
b11111010111110101111101000011100 $
b11111010111110101111101000011100 *
b11100 %
b11100 +
1#
#290
0#
#295
b11111010111110101111101000011101 $
b11111010111110101111101000011101 *
b11101 %
b11101 +
1#
#300
0#
#305
b11111010111110101111101000011110 $
b11111010111110101111101000011110 *
b11110 %
b11110 +
1#
#310
0#
#315
b11111010111110101111101000011111 $
b11111010111110101111101000011111 *
b11111 %
b11111 +
1#
#320
0#
#325
b0 %
b0 +
b0 $
b0 *
0)
1#
#330
0#
#335
b11111010111110101111101000000010 !
b11111010111110101111101000000010 .
b11111010111110101111101000000001 "
b11111010111110101111101000000001 /
1#
b10 '
b10 -
b1 &
b1 ,
#340
0#
#345
b11111010111110101111101000000100 !
b11111010111110101111101000000100 .
b11111010111110101111101000000011 "
b11111010111110101111101000000011 /
1#
b100 '
b100 -
b11 &
b11 ,
#350
0#
#355
b11111010111110101111101000000110 !
b11111010111110101111101000000110 .
b11111010111110101111101000000101 "
b11111010111110101111101000000101 /
1#
b110 '
b110 -
b101 &
b101 ,
#360
0#
#365
b11111010111110101111101000001000 !
b11111010111110101111101000001000 .
b11111010111110101111101000000111 "
b11111010111110101111101000000111 /
1#
b1000 '
b1000 -
b111 &
b111 ,
#370
0#
#375
b11111010111110101111101000001010 !
b11111010111110101111101000001010 .
b11111010111110101111101000001001 "
b11111010111110101111101000001001 /
1#
b1010 '
b1010 -
b1001 &
b1001 ,
#380
0#
#385
b11111010111110101111101000001100 !
b11111010111110101111101000001100 .
b11111010111110101111101000001011 "
b11111010111110101111101000001011 /
1#
b1100 '
b1100 -
b1011 &
b1011 ,
#390
0#
#395
b11111010111110101111101000001110 !
b11111010111110101111101000001110 .
b11111010111110101111101000001101 "
b11111010111110101111101000001101 /
1#
b1110 '
b1110 -
b1101 &
b1101 ,
#400
0#
#405
b11111010111110101111101000010000 !
b11111010111110101111101000010000 .
b11111010111110101111101000001111 "
b11111010111110101111101000001111 /
1#
b10000 '
b10000 -
b1111 &
b1111 ,
#410
0#
#415
b11111010111110101111101000010010 !
b11111010111110101111101000010010 .
b11111010111110101111101000010001 "
b11111010111110101111101000010001 /
1#
b10010 '
b10010 -
b10001 &
b10001 ,
#420
0#
#425
b11111010111110101111101000010100 !
b11111010111110101111101000010100 .
b11111010111110101111101000010011 "
b11111010111110101111101000010011 /
1#
b10100 '
b10100 -
b10011 &
b10011 ,
#430
0#
#435
b11111010111110101111101000010110 !
b11111010111110101111101000010110 .
b11111010111110101111101000010101 "
b11111010111110101111101000010101 /
1#
b10110 '
b10110 -
b10101 &
b10101 ,
#440
0#
#445
b11111010111110101111101000011000 !
b11111010111110101111101000011000 .
b11111010111110101111101000010111 "
b11111010111110101111101000010111 /
1#
b11000 '
b11000 -
b10111 &
b10111 ,
#450
0#
#455
b11111010111110101111101000011010 !
b11111010111110101111101000011010 .
b11111010111110101111101000011001 "
b11111010111110101111101000011001 /
1#
b11010 '
b11010 -
b11001 &
b11001 ,
#460
0#
#465
b11111010111110101111101000011100 !
b11111010111110101111101000011100 .
b11111010111110101111101000011011 "
b11111010111110101111101000011011 /
1#
b11100 '
b11100 -
b11011 &
b11011 ,
#470
0#
#475
b11111010111110101111101000011110 !
b11111010111110101111101000011110 .
b11111010111110101111101000011101 "
b11111010111110101111101000011101 /
1#
b11110 '
b11110 -
b11101 &
b11101 ,
#480
0#
#485
b0 !
b0 .
b11111010111110101111101000011111 "
b11111010111110101111101000011111 /
1#
b0 '
b0 -
b11111 &
b11111 ,
#490
0#
#495
b0 "
b0 /
1#
1(
#496
0(
