src/signExt.v
/*
Instruction [31:0]
─────────┐
         │
Opcode┌──▼──┐[31:0]
──────► Ext ├──────►Immediate
 [6:0]└─────┘        Value
*/

module signExt(opcode, instIn, immOut);
  input wire [6:0] opcode;
  input wire [31:0] instIn;
  output reg [31:0] immOut;
  always@(*)
    case(opcode)
      7'b0110111: begin // LUI 
        immOut[31:12] = instIn[31:12];
        immOut[11:0] = 12'b0;
      end
      7'b0010111: begin // AUIPC
        immOut[31:12] = instIn[31:12];
        immOut[11:0] = 12'b0;
      end
      7'b1101111: begin // JAL
        immOut = {{20{instIn[31]}}, instIn[19:12], instIn[13], instIn[30:21], 1'b0};
      end
      7'b1100111: begin // JALR
        immOut[11:0] = instIn[31:20];
        immOut[31:12] = {20{instIn[31]}};
      end
      7'b1100011: begin // Branches
        immOut = {{20{instIn[31]}}, instIn[7], instIn[30:25], instIn[11:8], 1'b0};
      end
      7'b0000011: begin // IL-Type
        immOut = {{20{instIn[31]}}, instIn[31:20]};
      end
      7'b0010011: begin // IR-Type
        immOut = (instIn[14:12] == (3'b001 | 3'b101)) ? {27'b0, instIn[24:20]} : {{20{instIn[31]}}, instIn[31:20]};
      end
      7'b0100011: begin
        immOut = {{20{instIn[31]}}, instIn[31:25], instIn[11:7]};
      end
      default:
        immOut = 32'b0;
    endcase
endmodule

tb/tb_signExt.v
module tb_signExt();
  reg [6:0] opcode_tb;
  reg [31:0] instIn_tb;
  wire [31:0] immOut_tb;
  signExt dut (.opcode(opcode_tb), 
               .instIn(instIn_tb), 
               .immOut(immOut_tb)
              );
  initial begin
    $dumpfile("signExt.vcd");
    $dumpvars(0, tb_signExt);
    instIn_tb = 32'hX;
    #1 opcode_tb = 7'b0110011; // R-type
    instIn_tb = 32'h00208033;  // 0x00000000
    #1 opcode_tb = 7'b0010011; // I-type
    instIn_tb = 32'h00b40413;  // 0x0000000B
    #1 opcode_tb = 7'b0010011; // I-type
    instIn_tb = 32'hff638393;  // 0xFFFFFFF6
    #1 opcode_tb = 7'b0100011; // S-type
    instIn_tb = 32'h00818323;  // 0x00000006
    #1 opcode_tb = 7'b0000011; // Load-type
    instIn_tb = 32'h00c18083;  // 0x0000000C
    #1 opcode_tb = 7'b0010011; // I-type - SRAI
    instIn_tb = 32'h4070d093;  // 0x00000007
    #1 opcode_tb = 7'b1100011; // B-type
    instIn_tb = 32'hfe000ae3;  // 0xFFFFFFF4
    #1 opcode_tb = 7'b1100111; // JALR
    instIn_tb = 32'h010100e7;  // 0x00000010
    #1 opcode_tb = 7'b1101111; // JAL
    instIn_tb = 32'h004000ef;  // 0x00000004
    #1 opcode_tb = 7'b0110111; // LUI
    instIn_tb = 32'hfffff037;  // 0xFFFFF000
    #1 opcode_tb = 7'b0010111; // AUIPC
    instIn_tb = 32'hf0101017;  // 0xF0101000
    #1 $finish;
  end
endmodule

pre_sim/signExt.vcd
$date
	Thu Nov  7 15:47:00 2024
$end
$version
	Icarus Verilog
$end
$timescale
	1s
$end
$scope module tb_signExt $end
$var wire 32 ! immOut_tb [31:0] $end
$var reg 32 " instIn_tb [31:0] $end
$var reg 7 # opcode_tb [6:0] $end
$scope module dut $end
$var wire 32 $ instIn [31:0] $end
$var wire 7 % opcode [6:0] $end
$var reg 32 & immOut [31:0] $end
$upscope $end
$upscope $end
$enddefinitions $end
#0
$dumpvars
bx &
bx %
bx $
bx #
bx "
bx !
$end
#1
b0 !
b0 &
b1000001000000000110011 "
b1000001000000000110011 $
b110011 #
b110011 %
#2
b1011 !
b1011 &
b101101000000010000010011 "
b101101000000010000010011 $
b10011 #
b10011 %
#3
b11111111111111111111111111110110 !
b11111111111111111111111111110110 &
b11111111011000111000001110010011 "
b11111111011000111000001110010011 $
#4
b110 !
b110 &
b100000011000001100100011 "
b100000011000001100100011 $
b100011 #
b100011 %
#5
b1100 !
b1100 &
b110000011000000010000011 "
b110000011000000010000011 $
b11 #
b11 %
#6
b111 !
b111 &
b1000000011100001101000010010011 "
b1000000011100001101000010010011 $
b10011 #
b10011 %
#7
b11111111111111111111111111110100 !
b11111111111111111111111111110100 &
b11111110000000000000101011100011 "
b11111110000000000000101011100011 $
b1100011 #
b1100011 %
#8
b10000 !
b10000 &
b1000000010000000011100111 "
b1000000010000000011100111 $
b1100111 #
b1100111 %
#9
b100 !
b100 &
b10000000000000011101111 "
b10000000000000011101111 $
b1101111 #
b1101111 %
#10
b11111111111111111111000000000000 !
b11111111111111111111000000000000 &
b11111111111111111111000000110111 "
b11111111111111111111000000110111 $
b110111 #
b110111 %
#11
b11110000000100000001000000000000 !
b11110000000100000001000000000000 &
b11110000000100000001000000010111 "
b11110000000100000001000000010111 $
b10111 #
b10111 %
